manufacture/__init__.py
manufacture/manufacture.py
manufacture-0.6.1.dist-info/LICENSE
manufacture-0.6.1.dist-info/METADATA
manufacture-0.6.1.dist-info/WHEEL
manufacture-0.6.1.dist-info/entry_points.txt
manufacture-0.6.1.dist-info/top_level.txt
manufacture-0.6.1.dist-info/RECORD
