Metadata-Version: 2.1
Name: manufacture
Version: 0.6.1
Summary: A simple command-line tool to create and manage files.
Home-page: https://github.com/Spandan7724/manufacture.git
Author: Spandan Chavan
Author-email: spandanchavan727477@gmail.com
Classifier: Programming Language :: Python :: 3
Classifier: License :: OSI Approved :: MIT License
Classifier: Operating System :: OS Independent
Requires-Python: >=3.6
License-File: LICENSE
